codefree/__init__.py
codefree/codefree.py
codefree/sources/__init__.py
codefree/sources/baseengine.py
codefree/sources/stackoverflow.py
codefree-0.1.3.dist-info/LICENSE
codefree-0.1.3.dist-info/METADATA
codefree-0.1.3.dist-info/WHEEL
codefree-0.1.3.dist-info/top_level.txt
codefree-0.1.3.dist-info/zip-safe
codefree-0.1.3.dist-info/RECORD
