Metadata-Version: 2.1
Name: codefree
Version: 0.1.3
Summary: CodeFree: Make no code a reality.
Home-page: https://github.com/CharlesPikachu/codefree
Author: Charles
Author-email: charlesblwx@gmail.com
License: Apache License 2.0
Platform: UNKNOWN
Classifier: License :: OSI Approved :: Apache Software License
Classifier: Programming Language :: Python :: 3
Classifier: Intended Audience :: Developers
Classifier: Operating System :: OS Independent
License-File: LICENSE
Requires-Dist: requests
Requires-Dist: pyflakes
